zephyr_gcp/__init__.py
zephyr_ai_gcp-0.0.1.dist-info/METADATA
zephyr_ai_gcp-0.0.1.dist-info/WHEEL
zephyr_ai_gcp-0.0.1.dist-info/top_level.txt
zephyr_ai_gcp-0.0.1.dist-info/RECORD
