Metadata-Version: 2.4
Name: zephyr-ai-gcp
Version: 0.0.1
Summary: Placeholder distribution reserving the Zephyr AI GCP integration name.
Author-email: Zephyr Team <dev@zephyr-ai.io>
License: Proprietary
Project-URL: Homepage, https://github.com/your-org/zephyr-ai
Project-URL: Source, https://github.com/your-org/zephyr-ai
Classifier: Development Status :: 2 - Pre-Alpha
Classifier: Programming Language :: Python :: 3
Requires-Python: >=3.10
Requires-Dist: zephyr-ai
